pyroll/freiberg_spreading/__init__.py
pyroll/freiberg_spreading/coefficients_lib.py
pyroll/freiberg_spreading/freiberg_spreading.py
pyroll/freiberg_spreading/hookspecs.py
pyroll/freiberg_spreading/materials.py
pyroll/freiberg_spreading/passes/__init__.py
pyroll/freiberg_spreading/passes/diamond_diamond.py
pyroll/freiberg_spreading/passes/diamond_square.py
pyroll/freiberg_spreading/passes/oval_round.py
pyroll/freiberg_spreading/passes/oval_square.py
pyroll/freiberg_spreading/passes/round_oval.py
pyroll/freiberg_spreading/passes/square_diamond.py
pyroll/freiberg_spreading/passes/square_oval.py
pyroll_freiberg_spreading-2.0.2.dist-info/METADATA
pyroll_freiberg_spreading-2.0.2.dist-info/WHEEL
pyroll_freiberg_spreading-2.0.2.dist-info/RECORD
