Metadata-Version: 2.4
Name: pyroll-freiberg-spreading
Version: 2.0.2
Summary: Plugin for PyRolL providing the Freiberg empirical spreading model.
Project-URL: Homepage, https://pyroll-project.github.io
Project-URL: Repository, https://github.com/pyroll-project/pyroll-freiberg-spreading
Project-URL: Documentation, https://github.com/pyroll-project/pyroll-freiberg-spreading/blob/main/docs/docs.pdf
Author-email: Max Weiner <max.weiner@imf.tu-freiberg.de>, Christoph Renzing <christoph.renzing@imf.tu-freiberg.de>, Matthias Schmidtchen <matthias.schmidtchen@imf.tu-freiberg.de>
License-Expression: BSD-3-Clause
Classifier: Development Status :: 5 - Production/Stable
Classifier: Framework :: Hatch
Classifier: Framework :: IPython
Classifier: Framework :: Jupyter
Classifier: Framework :: Pytest
Classifier: Framework :: Sphinx
Classifier: Intended Audience :: Manufacturing
Classifier: Intended Audience :: Science/Research
Classifier: License :: OSI Approved :: BSD License
Classifier: Natural Language :: English
Classifier: Operating System :: OS Independent
Classifier: Programming Language :: Python :: 3
Classifier: Programming Language :: Python :: 3.9
Classifier: Programming Language :: Python :: 3.10
Classifier: Programming Language :: Python :: 3.11
Classifier: Topic :: Scientific/Engineering
Requires-Python: <4.0,>=3.9
Requires-Dist: pyroll-core~=2.1
